letter2/__init__.py
letter2/core.py
letter2/database.py
letter2/utils.py
letter2-0.0.5.dist-info/METADATA
letter2-0.0.5.dist-info/WHEEL
letter2-0.0.5.dist-info/top_level.txt
letter2-0.0.5.dist-info/RECORD
