Metadata-Version: 2.1
Name: letter2
Version: 0.0.5
Summary: 一个简单的基于 socket 的聊天室
Home-page: 
Author: violet drowning
Author-email: 
Classifier: Programming Language :: Python :: 3
Classifier: License :: OSI Approved :: MIT License
Classifier: Operating System :: OS Independent
Requires-Python: >=3.6
